CHANGES
LICENSE
README.txt
bootstrap.py
buildout.cfg
setup.py
iw/__init__.py
iw.dist.egg-info/PKG-INFO
iw.dist.egg-info/SOURCES.txt
iw.dist.egg-info/dependency_links.txt
iw.dist.egg-info/entry_points.txt
iw.dist.egg-info/namespace_packages.txt
iw.dist.egg-info/not-zip-safe
iw.dist.egg-info/requires.txt
iw.dist.egg-info/top_level.txt
iw/dist/README.txt
iw/dist/__init__.py
iw/dist/core.py
iw/dist/mregister.py
iw/dist/mupload.py
iw/dist/pypirc.py
iw/dist/docs/README.txt
iw/dist/doctests/README.txt
iw/dist/tests/__init__.py
iw/dist/tests/test_distdocs.py
iw/dist/tests/test_distdocstrings.py
iw/dist/tests/test_mregister.py
iw/dist/tests/test_mupload.py
iw/dist/tests/test_pypirc.py
