Metadata-Version: 1.0
Name: iw.dist
Version: 0.1.8
Summary: Distutils commands to upload files to several servers
Home-page: https://ingeniweb.svn.sourceforge.net/svnroot/ingeniweb/iw.dist
Author: Ingeniweb
Author-email: support@ingeniweb.com
License: GPL
Platform: UNKNOWN
Classifier: Programming Language :: Python
Classifier: Topic :: Software Development :: Libraries :: Python Modules
